projektor/__init__.py
projektor/cli.py
projektor/analysis/__init__.py
projektor/analysis/metrics.py
projektor/analysis/reports.py
projektor/analysis/toon_parser.py
projektor/core/__init__.py
projektor/core/config.py
projektor/core/events.py
projektor/core/project.py
projektor/core/ticket.py
projektor/devops/__init__.py
projektor/devops/code_executor.py
projektor/devops/git_ops.py
projektor/devops/test_runner.py
projektor/integration/__init__.py
projektor/integration/config_loader.py
projektor/integration/decorators.py
projektor/integration/error_handler.py
projektor/integration/hooks.py
projektor/integration/installer.py
projektor/integration/pytest_plugin.py
projektor/orchestration/__init__.py
projektor/orchestration/executor.py
projektor/orchestration/orchestrator.py
projektor/orchestration/planner.py
projektor/planning/__init__.py
projektor/planning/backlog.py
projektor/planning/milestone.py
projektor/planning/roadmap.py
projektor/planning/sprint.py
projektor-0.1.15.dist-info/METADATA
projektor-0.1.15.dist-info/WHEEL
projektor-0.1.15.dist-info/entry_points.txt
projektor-0.1.15.dist-info/licenses/LICENSE
projektor-0.1.15.dist-info/RECORD
