Metadata-Version: 2.4
Name: projektor
Version: 0.1.15
Summary: LLM-orchestrated project management with DevOps automation for iterative development
Project-URL: Homepage, https://github.com/softreck/projektor
Project-URL: Documentation, https://projektor.readthedocs.io
Project-URL: Repository, https://github.com/softreck/projektor
Project-URL: Issues, https://github.com/softreck/projektor/issues
Author-email: Softreck <info@softreck.dev>
License: Apache-2.0
License-File: LICENSE
Keywords: agile,automation,ci-cd,devops,llm,orchestration,project-management,roadmap,tickets
Classifier: Development Status :: 3 - Alpha
Classifier: Intended Audience :: Developers
Classifier: License :: OSI Approved :: Apache Software License
Classifier: Operating System :: OS Independent
Classifier: Programming Language :: Python :: 3
Classifier: Programming Language :: Python :: 3.10
Classifier: Programming Language :: Python :: 3.11
Classifier: Programming Language :: Python :: 3.12
Classifier: Topic :: Software Development :: Build Tools
Classifier: Topic :: Software Development :: Quality Assurance
Classifier: Topic :: Software Development :: Testing
Requires-Python: >=3.10
Requires-Dist: click>=8.0
Requires-Dist: httpx>=0.25.0
Requires-Dist: jinja2>=3.0
Requires-Dist: pydantic>=2.0
Requires-Dist: python-dotenv>=1.0.0
Requires-Dist: pyyaml>=6.0
Requires-Dist: rich>=13.0
Provides-Extra: all
Requires-Dist: black>=23.0; extra == 'all'
Requires-Dist: litellm>=1.30.0; extra == 'all'
Requires-Dist: mypy>=1.0; extra == 'all'
Requires-Dist: pytest-asyncio>=0.21; extra == 'all'
Requires-Dist: pytest-cov>=4.0; extra == 'all'
Requires-Dist: pytest>=7.0; extra == 'all'
Requires-Dist: ruff>=0.1.0; extra == 'all'
Requires-Dist: toml>=0.10.0; extra == 'all'
Provides-Extra: dev
Requires-Dist: black>=23.0; extra == 'dev'
Requires-Dist: mypy>=1.0; extra == 'dev'
Requires-Dist: pytest-asyncio>=0.21; extra == 'dev'
Requires-Dist: pytest-cov>=4.0; extra == 'dev'
Requires-Dist: pytest>=7.0; extra == 'dev'
Requires-Dist: ruff>=0.1.0; extra == 'dev'
Requires-Dist: toml>=0.10.0; extra == 'dev'
Provides-Extra: llm
Requires-Dist: litellm>=1.30.0; extra == 'llm'
